vimusic_converter/__init__.py
vimusic_converter/__main__.py
vimusic_converter/dbhandler.py
vimusic_converter/spotify.py
vimusic_converter-0.1.dist-info/METADATA
vimusic_converter-0.1.dist-info/WHEEL
vimusic_converter-0.1.dist-info/top_level.txt
vimusic_converter-0.1.dist-info/RECORD
