Metadata-Version: 2.1
Name: vimusic_converter
Version: 0.1
Summary: Convert ViMusic Playlists into playlists for other platforms
Author: nulladmin1 (Shrey Deogade)
Author-email: shrey.deogade@protonmail.com
Classifier: Development Status :: 3 - Alpha
Classifier: Intended Audience :: Developers
Classifier: Intended Audience :: End Users/Desktop
Classifier: Programming Language :: Python :: 3 :: Only
Classifier: Operating System :: OS Independent
Classifier: License :: OSI Approved :: GNU General Public License v3 (GPLv3)
Requires-Dist: python-dotenv
Requires-Dist: requests
Requires-Dist: spotipy
